mlflow_user/__init__.py
mlflow_user/app.py
mlflow_user-0.1.0.dist-info/WHEEL
mlflow_user-0.1.0.dist-info/METADATA
mlflow_user-0.1.0.dist-info/RECORD
