Metadata-Version: 2.1
Name: mlflow-user
Version: 0.1.0
Summary: A plugin for MLflow to users and permissions
Author: Abdullah Ahmed
Author-email: abdullah_ahmed@uk.hrdeu.com
Requires-Python: >=3.10,<4.0
Classifier: Programming Language :: Python :: 3
Classifier: Programming Language :: Python :: 3.10
